<annotation>
	<folder>Truk3GandarSamping</folder>
	<filename>truck3-30167.jpg</filename>
	<path>C:\Users\xwyzworm\Documents\Semester 8\EndtoEndWeightEstimation\ModelDevelopment\model_data\labelledData\Truk3GandarSamping\truck3-30167.jpg</path>
	<source>
		<database>Unknown</database>
	</source>
	<size>
		<width>512</width>
		<height>240</height>
		<depth>3</depth>
	</size>
	<segmented>0</segmented>
	<object>
		<name>truk_3_gandar</name>
		<pose>Unspecified</pose>
		<truncated>0</truncated>
		<difficult>0</difficult>
		<bndbox>
			<xmin>21</xmin>
			<ymin>18</ymin>
			<xmax>471</xmax>
			<ymax>222</ymax>
		</bndbox>
	</object>
</annotation>
